nyxus/backend.cp310-win_amd64.pyd
nyxus/functions.py
nyxus/interface.py
nyxus/nyxus.py
nyxus/_version.py
nyxus/__init__.py
nyxus_cuda12x-0.9.3.dist-info/DELVEWHEEL
nyxus_cuda12x-0.9.3.dist-info/LICENSE
nyxus_cuda12x-0.9.3.dist-info/METADATA
nyxus_cuda12x-0.9.3.dist-info/RECORD
nyxus_cuda12x-0.9.3.dist-info/top_level.txt
nyxus_cuda12x-0.9.3.dist-info/WHEEL
nyxus_cuda12x.libs/arrow-5e09a73314880eca3b94488393eae0aa.dll
nyxus_cuda12x.libs/cudart64_12-f95273031fc5ea44cdb37e0a696a1b15.dll
nyxus_cuda12x.libs/dcmdata-810411589e11001a2fdff2a808c212de.dll
nyxus_cuda12x.libs/dcmfg-5310b46544cda54476cabb5a186e0336.dll
nyxus_cuda12x.libs/dcmimgle-28f23822d101a8cc4d86da31327af309.dll
nyxus_cuda12x.libs/dcmiod-29c659b2ecfe2fdb19bd9b81007344de.dll
nyxus_cuda12x.libs/dcmjpeg-a410d2c513eb01b785ec4f80247ac24b.dll
nyxus_cuda12x.libs/dcmjpls-12e32ab3b52e83f90ce3a825ac3c2972.dll
nyxus_cuda12x.libs/dcmseg-274a4afbf6297fec43f389a7f900a9a9.dll
nyxus_cuda12x.libs/dcmtkcharls-031d90a7f5c478eba3d9d0e92354139e.dll
nyxus_cuda12x.libs/deflate-a0ce8804719ea25977cb8220ed6ad7e0.dll
nyxus_cuda12x.libs/fmjpeg2k-4faa522ddce8aaad5bbb656e70736e69.dll
nyxus_cuda12x.libs/ijg12-bf360b75926f7145a25066f847340846.dll
nyxus_cuda12x.libs/ijg16-3984cc20d2a932b9c5a7bd412dc33fe6.dll
nyxus_cuda12x.libs/ijg8-4b02f213c5444bce66a5a57ce8f8cc6c.dll
nyxus_cuda12x.libs/jpeg62-a426853bcb3cb51f4749b4b5024ff083.dll
nyxus_cuda12x.libs/msvcp140-0f885b509a685d2bbfa652fed26b5fb3.dll
nyxus_cuda12x.libs/oficonv-c6bcdb656d7867410c1eeff6ab8dfa3c.dll
nyxus_cuda12x.libs/oflog-6ecac9fe1de9b88460ab9ff2c145d355.dll
nyxus_cuda12x.libs/ofstd-3b58c9cbc361bb5c0db927be1a7543e8.dll
nyxus_cuda12x.libs/openjp2-2457cef9b107dee61441b5dc9de5856e.dll
nyxus_cuda12x.libs/parquet-7b50c88e19bc1d80d07ec5a0f1a349ff.dll
nyxus_cuda12x.libs/tiff-7c2d3d6bdbf16856acdce318bc40ccbe.dll
nyxus_cuda12x.libs/zlib-8b37ef82e4e2a3eca9b191521e44b469.dll
