Metadata-Version: 2.1
Name: nyxus-cuda12x
Version: 0.9.3
Summary: Scalable library for calculating features from intensity-label image data
Home-page: https://github.com/PolusAI/nyxus
Author: Andriy Kharchenko
Author-email: andriy.kharchenko@axleinfo.com
Requires-Python: >=3.8
License-File: LICENSE
Requires-Dist: numpy
Requires-Dist: pandas
